nwt_dataset_cli/__init__.py
nwt_dataset_cli/app.py
nwt_dataset_cli/dtos.py
nwt_dataset_cli/helpers/helpers.py
nwt_dataset_cli/helpers/options.py
nwt_dataset_cli/services/dataset_service.py
nwt_dataset_cli/settings.py
nwt_dataset_cli-1.2.0.dist-info/entry_points.txt
nwt_dataset_cli-1.2.0.dist-info/WHEEL
nwt_dataset_cli-1.2.0.dist-info/METADATA
nwt_dataset_cli-1.2.0.dist-info/RECORD
