Metadata-Version: 2.1
Name: nwt-dataset-cli
Version: 1.2.0
Summary: Dataset Generate CLI
Home-page: https://bitbucket.org/newtralmedia/dataset-cli-lib
Author: Pablo Alvarez
Author-email: pablo.alvarez@newtral.es
Requires-Python: >=3.8,<3.9
Classifier: Programming Language :: Python :: 3
Classifier: Programming Language :: Python :: 3.8
Requires-Dist: pandas (>=1.1.3,<2.0.0)
Requires-Dist: pymongo (>=3.11.0,<4.0.0)
Requires-Dist: sklearn (>=0.0,<0.1)
Requires-Dist: typer[all] (>=0.3.2,<0.4.0)
Project-URL: Repository, https://bitbucket.org/newtralmedia/dataset-cli-lib
